pyanimation/__init__.py
pyanimation/animation.py
pyanimation-0.7.dist-info/DESCRIPTION.rst
pyanimation-0.7.dist-info/METADATA
pyanimation-0.7.dist-info/RECORD
pyanimation-0.7.dist-info/WHEEL
pyanimation-0.7.dist-info/metadata.json
pyanimation-0.7.dist-info/top_level.txt
