Metadata-Version: 2.0
Name: pyanimation
Version: 0.7
Summary: A pygame animation package
Home-page: https://github.com/estevaofon/pyanimation
Author: Estevao Fonseca
Author-email: estevaopfon@gmail.com
License: MIT
Keywords: pygame,animation,pyanimation
Platform: UNKNOWN
Classifier: Development Status :: 3 - Alpha
Classifier: Intended Audience :: Developers
Classifier: License :: OSI Approved :: MIT License
Classifier: Programming Language :: Python :: 2
Classifier: Programming Language :: Python :: 2.7
Classifier: Programming Language :: Python :: 3
Classifier: Programming Language :: Python :: 3.4
Classifier: Programming Language :: Python :: 3.5
Classifier: Programming Language :: Python :: 3.6
Requires-Dist: pygame
